tests4py/__init__.py
tests4py/constants.py
tests4py/environment.py
tests4py/logger.py
tests4py/api/__init__.py
tests4py/api/cache.py
tests4py/api/config.py
tests4py/api/default.py
tests4py/api/logging.py
tests4py/api/report.py
tests4py/api/test.py
tests4py/api/utils.py
tests4py/cli/__init__.py
tests4py/cli/framework/__init__.py
tests4py/cli/framework/cache.py
tests4py/cli/framework/config.py
tests4py/cli/framework/default.py
tests4py/cli/framework/grammar.py
tests4py/cli/framework/sfl.py
tests4py/cli/framework/systemtest.py
tests4py/cli/framework/unittest.py
tests4py/grammars/__init__.py
tests4py/grammars/antlr.py
tests4py/grammars/default.py
tests4py/grammars/fuzzer.py
tests4py/grammars/parser.py
tests4py/grammars/python.py
tests4py/grammars/tree.py
tests4py/grammars/utils.py
tests4py/projects/__init__.py
tests4py/projects/ansible.py
tests4py/projects/black.py
tests4py/projects/calculator.py
tests4py/projects/cookiecutter.py
tests4py/projects/expression.py
tests4py/projects/fastapi.py
tests4py/projects/httpie.py
tests4py/projects/keras.py
tests4py/projects/luigi.py
tests4py/projects/markup.py
tests4py/projects/matplotlib.py
tests4py/projects/middle.py
tests4py/projects/pandas.py
tests4py/projects/pysnooper.py
tests4py/projects/sanic.py
tests4py/projects/scrapy.py
tests4py/projects/spacy.py
tests4py/projects/thefuck.py
tests4py/projects/tornado.py
tests4py/projects/tqdm.py
tests4py/projects/youtubedl.py
tests4py/projects/resources/__init__.py
tests4py/projects/resources/ansible/__init__.py
tests4py/projects/resources/ansible/requirements.txt
tests4py/projects/resources/ansible/bug_1/__init__.py
tests4py/projects/resources/ansible/bug_1/fix.patch
tests4py/projects/resources/ansible/bug_10/__init__.py
tests4py/projects/resources/ansible/bug_10/fix.patch
tests4py/projects/resources/ansible/bug_11/__init__.py
tests4py/projects/resources/ansible/bug_11/fix.patch
tests4py/projects/resources/ansible/bug_12/__init__.py
tests4py/projects/resources/ansible/bug_12/fix.patch
tests4py-0.0.13.dist-info/LICENSE
tests4py-0.0.13.dist-info/METADATA
tests4py-0.0.13.dist-info/WHEEL
tests4py-0.0.13.dist-info/entry_points.txt
tests4py-0.0.13.dist-info/top_level.txt
tests4py-0.0.13.dist-info/RECORD
