Metadata-Version: 2.1
Name: tests4py
Version: 0.0.13
Summary: Tests4Py a benchmark for testing bugs
Author-email: Marius Smytzek <marius.smytzek@cispa.de>, Martin Eberlein <ebermart@informatik.hu-berlin.de>, Batuhan Serce <batuhan.serce@cispa.de>
Project-URL: Homepage, https://github.com/smythi93/Tests4Py
Project-URL: Bug Tracker, https://github.com/smythi93/Tests4Py/issues
Classifier: Intended Audience :: Science/Research
Classifier: License :: OSI Approved :: MIT License
Classifier: Programming Language :: Python :: 3.10
Classifier: Operating System :: OS Independent
Classifier: Topic :: Scientific/Engineering
Classifier: Topic :: Software Development :: Testing
Requires-Python: >=3.10
License-File: LICENSE
Requires-Dist: tabulate >=0.9.0
Requires-Dist: sflkit >=0.2.22
Requires-Dist: sflkitlib >=0.0.5
Requires-Dist: unidiff >=0.7.5
Requires-Dist: psutil >=5.9.5
Provides-Extra: test
Requires-Dist: pytest >=7.2.2 ; extra == 'test'
Requires-Dist: pytest-cov >=4.1.0 ; extra == 'test'
Requires-Dist: pytest-html >=3.2.0 ; extra == 'test'
Requires-Dist: pytest-rerunfailures >=11.1.2 ; extra == 'test'
Requires-Dist: parameterized >=0.8.1 ; extra == 'test'
